owll/__init__.py
owll/owll.py
owll-1.1.4.dist-info/METADATA
owll-1.1.4.dist-info/WHEEL
owll-1.1.4.dist-info/entry_points.txt
owll-1.1.4.dist-info/top_level.txt
owll-1.1.4.dist-info/RECORD
